snakemake_interface_common/__init__.py
snakemake_interface_common/_common.py
snakemake_interface_common/exceptions.py
snakemake_interface_common/io.py
snakemake_interface_common/logging.py
snakemake_interface_common/py.typed
snakemake_interface_common/rules.py
snakemake_interface_common/settings.py
snakemake_interface_common/utils.py
snakemake_interface_common/plugin_registry/__init__.py
snakemake_interface_common/plugin_registry/attribute_types.py
snakemake_interface_common/plugin_registry/plugin.py
snakemake_interface_common/plugin_registry/tests.py
snakemake_interface_common-1.21.0.dist-info/licenses/LICENSE
snakemake_interface_common-1.21.0.dist-info/METADATA
snakemake_interface_common-1.21.0.dist-info/WHEEL
snakemake_interface_common-1.21.0.dist-info/top_level.txt
snakemake_interface_common-1.21.0.dist-info/RECORD
