Metadata-Version: 2.4
Name: snakemake-interface-common
Version: 1.21.0
Summary: Common functions and classes for Snakemake and its plugins
Author-email: Johannes Koester <johannes.koester@uni-due.de>
Requires-Python: >=3.8
License-File: LICENSE
Requires-Dist: argparse-dataclass>=2.0.0
Requires-Dist: ConfigArgParse>=1.7
Requires-Dist: packaging<26.0,>=24.0
Dynamic: license-file
